code_cantation/__init__.py
code_cantation/cli.py
code_cantation/code_utils.py
code_cantation/executor.py
code_cantation/models.py
code_cantation/safety_checker.py
code_cantation/server.py
code_cantation-0.1.1.dist-info/METADATA
code_cantation-0.1.1.dist-info/WHEEL
code_cantation-0.1.1.dist-info/entry_points.txt
code_cantation-0.1.1.dist-info/top_level.txt
code_cantation-0.1.1.dist-info/RECORD
