Metadata-Version: 2.4
Name: code-cantation
Version: 0.1.1
Summary: safely execute python come. built in safety checker. use it as cli, library, server
Author-email: thecoderide <thecoderider42@gmail.com>
Requires-Python: >=3.10
Requires-Dist: pydantic==2.10.5
Requires-Dist: dill==0.3.9
Provides-Extra: server
Requires-Dist: fastapi==0.115.12; extra == "server"
Requires-Dist: uvicorn==0.34.2; extra == "server"
